munchkinapi/__init__.py
munchkinapi/conftest.py
munchkinapi/models/__init__.py
munchkinapi/models/cards/__init__.py
munchkinapi/models/cards/base.py
munchkinapi/models/cards/doors/__init__.py
munchkinapi/models/cards/doors/base.py
munchkinapi/models/cards/doors/test_card.py
munchkinapi/models/cards/doors/test_card2.py
munchkinapi/models/cards/schemas/__init__.py
munchkinapi/models/cards/schemas/card.py
munchkinapi/models/cards/schemas/door_card.py
munchkinapi/models/cards/schemas/treasure_card.py
munchkinapi/models/cards/treasures/__init__.py
munchkinapi/models/cards/treasures/base.py
munchkinapi/models/cards/treasures/sports_drink.py
munchkinapi/models/cards/utils/__init__.py
munchkinapi-0.0.1.dist-info/METADATA
munchkinapi-0.0.1.dist-info/WHEEL
munchkinapi-0.0.1.dist-info/top_level.txt
munchkinapi-0.0.1.dist-info/RECORD
